{
  "count": 6,
  "colors": [
    {
      "rgba_be": "#45288548",
      "argb_le": "#48852845",
      "bytes": [
        69,
        40,
        133,
        72
      ]
    },
    {
      "rgba_be": "#c7380549",
      "argb_le": "#490538c7",
      "bytes": [
        199,
        56,
        5,
        73
      ]
    },
    {
      "rgba_be": "#49494759",
      "argb_le": "#59474949",
      "bytes": [
        73,
        73,
        71,
        89
      ]
    },
    {
      "rgba_be": "#cf5a8c72",
      "argb_le": "#728c5acf",
      "bytes": [
        207,
        90,
        140,
        114
      ]
    },
    {
      "rgba_be": "#cc61ca71",
      "argb_le": "#71ca61cc",
      "bytes": [
        204,
        97,
        202,
        113
      ]
    },
    {
      "rgba_be": "#9cffd7d5",
      "argb_le": "#d5d7ff9c",
      "bytes": [
        156,
        255,
        215,
        213
      ]
    }
  ]
}