{
  "count": 8,
  "colors": [
    {
      "rgba_be": "#45314120",
      "argb_le": "#20413145",
      "bytes": [
        69,
        49,
        65,
        32
      ]
    },
    {
      "rgba_be": "#c6518138",
      "argb_le": "#388151c6",
      "bytes": [
        198,
        81,
        129,
        56
      ]
    },
    {
      "rgba_be": "#877ac260",
      "argb_le": "#60c27a87",
      "bytes": [
        135,
        122,
        194,
        96
      ]
    },
    {
      "rgba_be": "#cb8ac370",
      "argb_le": "#70c38acb",
      "bytes": [
        203,
        138,
        195,
        112
      ]
    },
    {
      "rgba_be": "#cea34481",
      "argb_le": "#8144a3ce",
      "bytes": [
        206,
        163,
        68,
        129
      ]
    },
    {
      "rgba_be": "#51b48599",
      "argb_le": "#9985b451",
      "bytes": [
        81,
        180,
        133,
        153
      ]
    },
    {
      "rgba_be": "#95cd07aa",
      "argb_le": "#aa07cd95",
      "bytes": [
        149,
        205,
        7,
        170
      ]
    },
    {
      "rgba_be": "#58ee48ca",
      "argb_le": "#ca48ee58",
      "bytes": [
        88,
        238,
        72,
        202
      ]
    }
  ]
}