{
  "count": 4,
  "colors": [
    {
      "rgba_be": "#c4414111",
      "argb_le": "#114141c4",
      "bytes": [
        196,
        65,
        65,
        17
      ]
    },
    {
      "rgba_be": "#8762c14a",
      "argb_le": "#4ac16287",
      "bytes": [
        135,
        98,
        193,
        74
      ]
    },
    {
      "rgba_be": "#8b8b026c",
      "argb_le": "#6c028b8b",
      "bytes": [
        139,
        139,
        2,
        108
      ]
    },
    {
      "rgba_be": "#0bc503ad",
      "argb_le": "#ad03c50b",
      "bytes": [
        11,
        197,
        3,
        173
      ]
    }
  ]
}